_adt_pybinds.cpython-311-darwin.so
_core_pybinds.cpython-311-darwin.so
_ase_pybinds.cpython-311-darwin.so
projectaria_tools_dev-0.14.0.dist-info/RECORD
projectaria_tools_dev-0.14.0.dist-info/LICENSE
projectaria_tools_dev-0.14.0.dist-info/WHEEL
projectaria_tools_dev-0.14.0.dist-info/entry_points.txt
projectaria_tools_dev-0.14.0.dist-info/top_level.txt
projectaria_tools_dev-0.14.0.dist-info/METADATA
projectaria_tools/__init__.py
projectaria_tools/utils.py
projectaria_tools/core/stream_id.py
projectaria_tools/core/sophus.py
projectaria_tools/core/mps.py
projectaria_tools/core/__init__.py
projectaria_tools/core/data_provider.py
projectaria_tools/core/sensor_data.py
projectaria_tools/core/image.py
projectaria_tools/core/calibration.py
projectaria_tools/projects/__init__.py
projectaria_tools/projects/adt/adt_challenge_dataset_downloader.py
projectaria_tools/projects/adt/__init__.py
projectaria_tools/projects/adt/utils.py
projectaria_tools/projects/adt/adt_challenge_prepare_submission.py
projectaria_tools/projects/adt/aria_digital_twin_downloader.py
projectaria_tools/projects/adt/adt_benchmark_dataset_downloader.py
projectaria_tools/projects/ase/__init__.py
projectaria_tools/.dylibs/libboost_chrono-mt.dylib
projectaria_tools/.dylibs/libboost_filesystem-mt.dylib
projectaria_tools/.dylibs/libboost_thread-mt.dylib
projectaria_tools/.dylibs/libpng16.16.dylib
projectaria_tools/.dylibs/liblz4.1.9.4.dylib
projectaria_tools/.dylibs/libboost_system-mt.dylib
projectaria_tools/.dylibs/libboost_atomic-mt.dylib
projectaria_tools/.dylibs/libboost_iostreams-mt.dylib
projectaria_tools/.dylibs/libturbojpeg.0.2.0.dylib
projectaria_tools/.dylibs/libfmt.9.1.0.dylib
projectaria_tools/.dylibs/liblzma.5.dylib
projectaria_tools/.dylibs/libboost_date_time-mt.dylib
projectaria_tools/.dylibs/libzstd.1.5.5.dylib
projectaria_tools/.dylibs/libjpeg.8.2.2.dylib
projectaria_tools/.dylibs/libxxhash.0.8.1.dylib
